Workbook

Sheet README
A1: Sales & Financial Performance Dashboard
A2: Advanced Excel Portfolio Project | Data Analyst
A4: PROJECT OVERVIEW
A5: This workbook simulates 2 years (2024-2025) of retail sales across 4 regions, 4 product categories, and 10 salespeople. It demonstrates advanced Excel skills used in real Data Analyst roles: formulas, dynamic summary tables, what-if analysis, and a KPI dashboard.
A7: SHEETS IN THIS WORKBOOK
A8: 1. README - this sheet
A9: 2. Raw_Sales_Data - 2,500+ row transactional dataset (source of truth for all formulas)
A10: 3. Formulas_Reference - live examples of XLOOKUP, INDEX-MATCH, SUMIFS, nested IF, commission logic
A11: 4. Pivot_Analysis - summary tables (Region x Month, Category, Top Salespeople) built with SUMIFS so they recalculate automatically when Raw_Sales_Data changes
A12: 5. What_If_Analysis - Scenario Manager style inputs (Best/Likely/Worst case) plus a one-variable data table showing profit sensitivity to discount %
A13: 6. Dashboard - KPI cards, interactive region filter (dropdown), and charts
A15: HOW TO EXTEND THIS IN EXCEL (steps that require the Excel desktop app itself)
... A30: Power Query-ready structured data, advanced formulas (XLOOKUP, INDEX-MATCH, SUMIFS, nested IF), dynamic summary tables, scenario/what-if analysis, conditional formatting KPI indicators, data validation dropdowns, interactive charts, dashboard design.

Sheet Dashboard
A1: SALES & FINANCIAL PERFORMANCE DASHBOARD
A2: FY 2024-2025 | All figures in INR
A4: Filter by Region: | B4: East
A6: Total Revenue | C6: Total Profit | E6: Avg Profit Margin | G6: Total Units Sold
A7: =IF($B$4="All",SUM(Raw_Sales_Data!$O$2:$O$2528),SUMIFS(Raw_Sales_Data!$O$2:$O$2528,Raw_Sales_Data!$E$2:$E$2528,$B$4)) -> 37965809 | C7: =IF($B$4="All",SUM(Raw_Sales_Data!$Q$2:$Q$2528),SUMIFS(Raw_Sales_Data!$Q$2:$Q$2528,Raw_Sales_Data!$E$2:$E$2528,$B$4)) -> 13188055 | E7: =IFERROR(IF($B$4="All",SUM(Raw_Sales_Data!$Q$2:$Q$2528)/SUM(Raw_Sales_Data!$O$2:$O$2528),SUMIFS(Raw_Sales_Data!$Q$2:$Q$2528,Raw_Sales_Data!$E$2:$E$2528,$B$4)/SUMIFS(Raw_Sales_Data!$O$2:$O$2528,Raw_Sales_Data!$E$2:$E$2528,$B$4)),0) -> 0.34736663 | G7: =IF($B$4="All",SUM(Raw_Sales_Data!$K$2:$K$2528),SUMIFS(Raw_Sales_Data!$K$2:$K$2528,Raw_Sales_Data!$E$2:$E$2528,$B$4)) -> 4258
A10: Category Breakdown (respects Region filter above) | D10: Month | E10: Revenue | G10: Salesperson | H10: Profit
A11: Category | B11: Revenue | D11: Jan | E11: =IF($B$4="All",SUMIFS(Raw_Sales_Data!$O$2:$O$2528,Raw_Sales_Data!$D$2:$D$2528,D11),SUMIFS(Raw_Sales_Data!$O$2:$O$2528,Raw_Sales_Data!$D$2:$D$2528,D11,Raw_Sales_Data!$E$2:$E$2528,$B$4)) -> 4311692.3 | G11: Aarav Shah | H11: =IF($B$4="All",SUMIFS(Raw_Sales_Data!$Q$2:$Q$2528,Raw_Sales_Data!$I$2:$I$2528,G11),SUMIFS(Raw_Sales_Data!$Q$2:$Q$2528,Raw_Sales_Data!$I$2:$I$2528,G11,Raw_Sales_Data!$E$2:$E$2528,$B$4)) -> 1823780.1
A12: Electronics | B12: =IF($B$4="All",SUMIFS(Raw_Sales_Data!$O$2:$O$2528,Raw_Sales_Data!$G$2:$G$2528,A12),SUMIFS(Raw_Sales_Data!$O$2:$O$2528,Raw_Sales_Data!$G$2:$G$2528,A12,Raw_Sales_Data!$E$2:$E$2528,$B$4)) -> 20698345 | D12: Feb | E12: =IF($B$4="All",SUMIFS(Raw_Sales_Data!$O$2:$O$2528,Raw_Sales_Data!$D$2:$D$2528,D12),SUMIFS(Raw_Sales_Data!$O$2:$O$2528,Raw_Sales_Data!$D$2:$D$2528,D12,Raw_Sales_Data!$E$2:$E$2528,$B$4)) -> 2666493.9 | G12: Priya Nair | H12: =IF($B$4="All",SUMIFS(Raw_Sales_Data!$Q$2:$Q$2528,Raw_Sales_Data!$I$2:$I$2528,G12),SUMIFS(Raw_Sales_Data!$Q$2:$Q$2528,Raw_Sales_Data!$I$2:$I$2528,G12,Raw_Sales_Data!$E$2:$E$2528,$B$4)) -> 797719.83
A13: Furniture | B13: =IF($B$4="All",SUMIFS(Raw_Sales_Data!$O$2:$O$2528,Raw_Sales_Data!$G$2:$G$2528,A13),SUMIFS(Raw_Sales_Data!$O$2:$O$2528,Raw_Sales_Data!$G$2:$G$2528,A13,Raw_Sales_Data!$E$2:$E$2528,$B$4)) -> 6765325.4 | D13: Mar | E13: =IF($B$4="All",SUMIFS(Raw_Sales_Data!$O$2:$O$2528,Raw_Sales_Data!$D$2:$D$2528,D13),SUMIFS(Raw_Sales_Data!$O$2:$O$2528,Raw_Sales_Data!$D$2:$D$2528,D13,Raw_Sales_Data!$E$2:$E$2528,$B$4)) -> 2541592.9 | G13: Rohan Mehta | H13: =IF($B$4="All",SUMIFS(Raw_Sales_Data!$Q$2:$Q$2528,Raw_Sales_Data!$I$2:$I$2528,G13),SUMIFS(Raw_Sales_Data!$Q$2:$Q$2528,Raw_Sales_Data!$I$2:$I$2528,G13,Raw_Sales_Data!$E$2:$E$2528,$B$4)) -> 1284178.6
A14: Apparel | B14: =IF($B$4="All",SUMIFS(Raw_Sales_Data!$O$2:$O$2528,Raw_Sales_Data!$G$2:$G$2528,A14),SUMIFS(Raw_Sales_Data!$O$2:$O$2528,Raw_Sales_Data!$G$2:$G$2528,A14,Raw_Sales_Data!$E$2:$E$2528,$B$4)) -> 2135538.2 | D14: Apr | E14: =IF($B$4="All",SUMIFS(Raw_Sales_Data!$O$2:$O$2528,Raw_Sales_Data!$D$2:$D$2528,D14),SUMIFS(Raw_Sales_Data!$O$2:$O$2528,Raw_Sales_Data!$D$2:$D$2528,D14,Raw_Sales_Data!$E$2:$E$2528,$B$4)) -> 3411546.8 | G14: Sneha Kulkarni | H14: =IF($B$4="All",SUMIFS(Raw_Sales_Data!$Q$2:$Q$2528,Raw_Sales_Data!$I$2:$I$2528,G14),SUMIFS(Raw_Sales_Data!$Q$2:$Q$2528,Raw_Sales_Data!$I$2:$I$2528,G14,Raw_Sales_Data!$E$2:$E$2528,$B$4)) -> 1289144.7
A15: Home Appliances | B15: =IF($B$4="All",SUMIFS(Raw_Sales_Data!$O$2:$O$2528,Raw_Sales_Data!$G$2:$G$2528,A15),SUMIFS(Raw_Sales_Data!$O$2:$O$2528,Raw_Sales_Data!$G$2:$G$2528,A15,Raw_Sales_Data!$E$2:$E$2528,$B$4)) -> 8366600 | D15: May | E15: =IF($B$4="All",SUMIFS(Raw_Sales_Data!$O$2:$O$2528,Raw_Sales_Data!$D$2:$D$2528,D15),SUMIFS(Raw_Sales_Data!$O$2:$O$2528,Raw_Sales_Data!$D$2:$D$2528,D15,Raw_Sales_Data!$E$2:$E$2528,$B$4)) -> 3803699 | G15: Vikram Rao | H15: =IF($B$4="All",SUMIFS(Raw_Sales_Data!$Q$2:$Q$2528,Raw_Sales_Data!$I$2:$I$2528,G15),SUMIFS(Raw_Sales_Data!$Q$2:$Q$2528,Raw_Sales_Data!$I$2:$I$2528,G15,Raw_Sales_Data!$E$2:$E$2528,$B$4)) -> 1273604.9
D16: Jun | E16: =IF($B$4="All",SUMIFS(Raw_Sales_Data!$O$2:$O$2528,Raw_Sales_Data!$D$2:$D$2528,D16),SUMIFS(Raw_Sales_Data!$O$2:$O$2528,Raw_Sales_Data!$D$2:$D$2528,D16,Raw_Sales_Data!$E$2:$E$2528,$B$4)) -> 4531325.6 | G16: Ananya Iyer | H16: =IF($B$4="All",SUMIFS(Raw_Sales_Data!$Q$2:$Q$2528,Raw_Sales_Data!$I$2:$I$2528,G16),SUMIFS(Raw_Sales_Data!$Q$2:$Q$2528,Raw_Sales_Data!$I$2:$I$2528,G16,Raw_Sales_Data!$E$2:$E$2528,$B$4)) -> 1385007.3
D17: Jul | E17: =IF($B$4="All",SUMIFS(Raw_Sales_Data!$O$2:$O$2528,Raw_Sales_Data!$D$2:$D$2528,D17),SUMIFS(Raw_Sales_Data!$O$2:$O$2528,Raw_Sales_Data!$D$2:$D$2528,D17,Raw_Sales_Data!$E$2:$E$2528,$B$4)) -> 3643023.1 | G17: Karan Malhotra | H17: =IF($B$4="All",SUMIFS(Raw_Sales_Data!$Q$2:$Q$2528,Raw_Sales_Data!$I$2:$I$2528,G17),SUMIFS(Raw_Sales_Data!$Q$2:$Q$2528,Raw_Sales_Data!$I$2:$I$2528,G17,Raw_Sales_Data!$E$2:$E$2528,$B$4)) -> 1388465.8
D18: Aug | E18: =IF($B$4="All",SUMIFS(Raw_Sales_Data!$O$2:$O$2528,Raw_Sales_Data!$D$2:$D$2528,D18),SUMIFS(Raw_Sales_Data!$O$2:$O$2528,Raw_Sales_Data!$D$2:$D$2528,D18,Raw_Sales_Data!$E$2:$E$2528,$B$4)) -> 3163030.5 | G18: Divya Reddy | H18: =IF($B$4="All",SUMIFS(Raw_Sales_Data!$Q$2:$Q$2528,Raw_Sales_Data!$I$2:$I$2528,G18),SUMIFS(Raw_Sales_Data!$Q$2:$Q$2528,Raw_Sales_Data!$I$2:$I$2528,G18,Raw_Sales_Data!$E$2:$E$2528,$B$4)) -> 1526842.2
D19: Sep | E19: =IF($B$4="All",SUMIFS(Raw_Sales_Data!$O$2:$O$2528,Raw_Sales_Data!$D$2:$D$2528,D19),SUMIFS(Raw_Sales_Data!$O$2:$O$2528,Raw_Sales_Data!$D$2:$D$2528,D19,Raw_Sales_Data!$E$2:$E$2528,$B$4)) -> 2633408.6 | G19: Arjun Kapoor | H19: =IF($B$4="All",SUMIFS(Raw_Sales_Data!$Q$2:$Q$2528,Raw_Sales_Data!$I$2:$I$2528,G19),SUMIFS(Raw_Sales_Data!$Q$2:$Q$2528,Raw_Sales_Data!$I$2:$I$2528,G19,Raw_Sales_Data!$E$2:$E$2528,$B$4)) -> 1353306
D20: Oct | E20: =IF($B$4="All",SUMIFS(Raw_Sales_Data!$O$2:$O$2528,Raw_Sales_Data!$D$2:$D$2528,D20),SUMIFS(Raw_Sales_Data!$O$2:$O$2528,Raw_Sales_Data!$D$2:$D$2528,D20,Raw_Sales_Data!$E$2:$E$2528,$B$4)) -> 2159157 | G20: Neha Joshi | H20: =IF($B$4="All",SUMIFS(Raw_Sales_Data!$Q$2:$Q$2528,Raw_Sales_Data!$I$2:$I$2528,G20),SUMIFS(Raw_Sales_Data!$Q$2:$Q$2528,Raw_Sales_Data!$I$2:$I$2528,G20,Raw_Sales_Data!$E$2:$E$2528,$B$4)) -> 1066005.8
D21: Nov | E21: =IF($B$4="All",SUMIFS(Raw_Sales_Data!$O$2:$O$2528,Raw_Sales_Data!$D$2:$D$2528,D21),SUMIFS(Raw_Sales_Data!$O$2:$O$2528,Raw_Sales_Data!$D$2:$D$2528,D21,Raw_Sales_Data!$E$2:$E$2528,$B$4)) -> 3390512.7
D22: Dec | E22: =IF($B$4="All",SUMIFS(Raw_Sales_Data!$O$2:$O$2528,Raw_Sales_Data!$D$2:$D$2528,D22),SUMIFS(Raw_Sales_Data!$O$2:$O$2528,Raw_Sales_Data!$D$2:$D$2528,D22,Raw_Sales_Data!$E$2:$E$2528,$B$4)) -> 1710326.2

Sheet Raw_Sales_Data
A1: Order ID | B1: Order Date | C1: Year | D1: Month | E1: Region | F1: City | G1: Category | H1: Product | I1: Salesperson | J1: Customer Segment | K1: Units Sold | L1: Unit Price | M1: Discount % | N1: Cost Ratio | O1: Revenue | P1: Cost | Q1: Profit | R1: Profit Margin %
A2: 1001 | B2: 2024-01-01 | C2: 2024 | D2: Jan | E2: North | F2: Lucknow | G2: Apparel | H2: T-Shirt | I2: Sneha Kulkarni | J2: Consumer | K2: 12 | L2: 768.2 | M2: 0.2 | N2: 0.72843591 | O2: =K2*L2*(1-M2) -> 7374.72 | P2: =O2*N2 -> 5372.0109 | Q2: =O2-P2 -> 2002.7091 | R2: =IF(O2=0,0,Q2/O2) -> 0.27156409
A3: 1002 | B3: 2024-01-01 | C3: 2024 | D3: Jan | E3: North | F3: Lucknow | G3: Home Appliances | H3: Mixer Grinder | I3: Aarav Shah | J3: Consumer | K3: 4 | L3: 3406.43 | M3: 0.15 | N3: 0.55530719 | O3: =K3*L3*(1-M3) -> 11581.862 | P3: =O3*N3 -> 6431.4913 | Q3: =O3-P3 -> 5150.3707 | R3: =IF(O3=0,0,Q3/O3) -> 0.44469281
A4: 1003 | B4: 2024-01-02 | C4: 2024 | D4: Jan | E4: East | F4: Kolkata | G4: Home Appliances | H4: Vacuum Cleaner | I4: Vikram Rao | J4: Consumer | K4: 3 | L4: 9688.23 | M4: 0.05 | N4: 0.60557427 | O4: =K4*L4*(1-M4) -> 27611.455 | P4: =O4*N4 -> 16720.787 | Q4: =O4-P4 -> 10890.669 | R4: =IF(O4=0,0,Q4/O4) -> 0.39442573
A5: 1004 | B5: 2024-01-02 | C5: 2024 | D5: Jan | E5: South | F5: Chennai | G5: Electronics | H5: Smartphone | I5: Karan Malhotra | J5: Consumer | K5: 6 | L5: 18625.49 | M5: 0.15 | N5: 0.60290417 | O5: =K5*L5*(1-M5) -> 94989.999 | P5: =O5*N5 -> 57269.867 | Q5: =O5-P5 -> 37720.132 | R5: =IF(O5=0,0,Q5/O5) -> 0.39709583
A6: 1005 | B6: 2024-01-02 | C6: 2024 | D6: Jan | E6: North | F6: Lucknow | G6: Home Appliances | H6: Vacuum Cleaner | I6: Priya Nair | J6: Corporate | K6: 2 | L6: 9549.44 | M6: 0.2 | N6: 0.67370395 | O6: =K6*L6*(1-M6) -> 15279.104 | P6: =O6*N6 -> 10293.593 | Q6: =O6-P6 -> 4985.5113 | R6: =IF(O6=0,0,Q6/O6) -> 0.32629605
A7: 1006 | B7: 2024-01-03 | C7: 2024 | D7: Jan | E7: South | F7: Hyderabad | G7: Electronics | H7: Smartphone | I7: Sneha Kulkarni | J7: Corporate | K7: 2 | L7: 18639.57 | M7: 0 | N7: 0.62602525 | O7: =K7*L7*(1-M7) -> 37279.14 | P7: =O7*N7 -> 23337.683 | Q7: =O7-P7 -> 13941.457 | R7: =IF(O7=0,0,Q7/O7) -> 0.37397475
A8: 1007 | B8: 2024-01-03 | C8: 2024 | D8: Jan | E8: East | F8: Patna | G8: Apparel | H8: T-Shirt | I8: Ananya Iyer | J8: Corporate | K8: 4 | L8: 813.61 | M8: 0.2 | N8: 0.73733092 | O8: =K8*L8*(1-M8) -> 2603.552 | P8: =O8*N8 -> 1919.6794 | Q8: =O8-P8 -> 683.87261 | R8: =IF(O8=0,0,Q8/O8) -> 0.26266908
A9: 1008 | B9: 2024-01-03 | C9: 2024 | D9: Jan | E9: North | F9: Lucknow | G9: Furniture | H9: Bookshelf | I9: Sneha Kulkarni | J9: Consumer | K9: 8 | L9: 4445.75 | M9: 0.2 | N9: 0.68763239 | O9: =K9*L9*(1-M9) -> 28452.8 | P9: =O9*N9 -> 19565.067 | Q9: =O9-P9 -> 8887.7331 | R9: =IF(O9=0,0,Q9/O9) -> 0.31236761
A10: 1009 | B10: 2024-01-03 | C10: 2024 | D10: Jan | E10: South | F10: Hyderabad | G10: Apparel | H10: T-Shirt | I10: Sneha Kulkarni | J10: Consumer | K10: 6 | L10: 792.09 | M10: 0 | N10: 0.59219657 | O10: =K10*L10*(1-M10) -> 4752.54 | P10: =O10*N10 -> 2814.4379 | Q10: =O10-P10 -> 1938.1021 | R10: =IF(O10=0,0,Q10/O10) -> 0.40780343
A11: 1010 | B11: 2024-01-04 | C11: 2024 | D11: Jan | E11: South | F11: Hyderabad | G11: Home Appliances | H11: Air Purifier | I11: Divya Reddy | J11: Consumer | K11: 5 | L11: 11567.56 | M11: 0.2 | N11: 0.66227363 | O11: =K11*L11*(1-M11) -> 46270.24 | P11: =O11*N11 -> 30643.56 | Q11: =O11-P11 -> 15626.68 | R11: =IF(O11=0,0,Q11/O11) -> 0.33772637
A12: 1011 | B12: 2024-01-04 | C12: 2024 | D12: Jan | E12: West | F12: Ahmedabad | G12: Home Appliances | H12: Vacuum Cleaner | I12: Karan Malhotra | J12: Corporate | K12: 4 | L12: 9972.46 | M12: 0 | N12: 0.65190526 | O12: =K12*L12*(1-M12) -> 39889.84 | P12: =O12*N12 -> 26004.396 | Q12: =O12-P12 -> 13885.444 | R12: =IF(O12=0,0,Q12/O12) -> 0.34809474
A13: 1012 | B13: 2024-01-04 | C13: 2024 | D13: Jan | E13: North | F13: Delhi | G13: Electronics | H13: Laptop | I13: Rohan Mehta | J13: Small Business | K13: 7 | L13: 55530.25 | M13: 0.1 | N13: 0.62632386 | O13: =K13*L13*(1-M13) -> 349840.58 | P13: =O13*N13 -> 219113.5 | Q13: =O13-P13 -> 130727.08 | R13: =IF(O13=0,0,Q13/O13) -> 0.37367614
... A2528: 3527 | B2528: 2025-12-31 | C2528: 2025 | D2528: Dec | E2528: South | F2528: Hyderabad | G2528: Furniture | H2528: Office Chair | I2528: Arjun Kapoor | J2528: Corporate | K2528: 11 | L2528: 6748.48 | M2528: 0 | N2528: 0.59765969 | O2528: =K2528*L2528*(1-M2528) -> 74233.28 | P2528: =O2528*N2528 -> 44366.239 | Q2528: =O2528-P2528 -> 29867.041 | R2528: =IF(O2528=0,0,Q2528/O2528) -> 0.40234031

Sheet Formulas_Reference
A1: Advanced Formula Reference
A2: Live formulas pulling from Raw_Sales_Data — change the input cells (blue) to see them update
A4: 1. SUMIFS — Conditional Aggregation
A5: Region | B5: South | C5: Total Revenue for Region: | D5: =SUMIFS(Raw_Sales_Data!$O$2:$O$2528,Raw_Sales_Data!$E$2:$E$2528,B5) -> 33845972
A6: Category | B6: Electronics | C6: Total Profit for Category: | D6: =SUMIFS(Raw_Sales_Data!$Q$2:$Q$2528,Raw_Sales_Data!$G$2:$G$2528,B6) -> 23826161
A7: Region + Category combined: | D7: =SUMIFS(Raw_Sales_Data!$O$2:$O$2528,Raw_Sales_Data!$E$2:$E$2528,B5,Raw_Sales_Data!$G$2:$G$2528,B6) -> 17181603
A9: 2. XLOOKUP — Exact Match Lookup
A10: Order ID | B10: 1011 | C10: Salesperson: | D10: =IFERROR(xlookup(B10,Raw_Sales_Data!$A$2:$A$2528,Raw_Sales_Data!$I$2:$I$2528),INDEX(Raw_Sales_Data!$I$2:$I$2528,MATCH(B10,Raw_Sales_Data!$A$2:$A$2528,0))) -> Karan Malhotra
C11: Revenue (₹): | D11: =IFERROR(xlookup(B10,Raw_Sales_Data!$A$2:$A$2528,Raw_Sales_Data!$O$2:$O$2528),INDEX(Raw_Sales_Data!$O$2:$O$2528,MATCH(B10,Raw_Sales_Data!$A$2:$A$2528,0))) -> 39889.84
A12: Note: formulas use IFERROR(XLOOKUP(...), INDEX/MATCH(...)) so this works in Excel 2019/LibreOffice (no native XLOOKUP) as well as Excel 365.
A14: 3. INDEX-MATCH — Flexible Two-Way Lookup
A15: Same Order ID as above: | C15: Category (INDEX-MATCH): | D15: =INDEX(Raw_Sales_Data!$G$2:$G$2528,MATCH(B10,Raw_Sales_Data!$A$2:$A$2528,0)) -> Home Appliances
A17: 4. Nested IF — Commission Tier Logic
A18: Salesperson | B18: Aarav Shah
A19: Total Revenue Generated: | B19: =SUMIFS(Raw_Sales_Data!$O$2:$O$2528,Raw_Sales_Data!$I$2:$I$2528,B18) -> 13592167
A20: Commission Tier: | B20: =IF(B19>3000000,"Gold - 8%",IF(B19>1500000,"Silver - 5%",IF(B19>0,"Bronze - 3%","No Sales"))) -> Gold - 8%
A21: Commission Amount (₹): | B21: =B19*IF(B19>3000000,0.08,IF(B19>1500000,0.05,IF(B19>0,0.03,0))) -> 1087373.4
A23: 5. Date & Text Functions
A24: Highest single-order Revenue: | B24: =MAX(Raw_Sales_Data!$O$2:$O$2528) -> 673217.76
A25: Average Order Value: | B25: =AVERAGE(Raw_Sales_Data!$O$2:$O$2528) -> 53772.695
A26: Total Orders (COUNTA): | B26: =COUNTA(Raw_Sales_Data!$A$2:$A$2528) -> 2527
A27: % of orders with a discount (COUNTIFS): | B27: =COUNTIFS(Raw_Sales_Data!$M$2:$M$2528,">0")/COUNTA(Raw_Sales_Data!$A$2:$A$2528) -> 0.66442422

Sheet Pivot_Analysis
A1: Pivot-Style Summary Tables
A2: Built with SUMIFS so tables auto-update when Raw_Sales_Data changes (in Excel, also try Insert > PivotTable on the same range for a native pivot)
A4: Region x Month Revenue Matrix (2025)
A5: Region | B5: Jan | C5: Feb | D5: Mar | E5: Apr | F5: May | G5: Jun | H5: Jul | I5: Aug | J5: Sep | K5: Oct | L5: Nov | M5: Dec | O5: Total
A6: North | B6: =SUMIFS(Raw_Sales_Data!$O$2:$O$2528,Raw_Sales_Data!$E$2:$E$2528,$A6,Raw_Sales_Data!$D$2:$D$2528,B$5,Raw_Sales_Data!$C$2:$C$2528,2025) -> 714837.24 | C6: =SUMIFS(Raw_Sales_Data!$O$2:$O$2528,Raw_Sales_Data!$E$2:$E$2528,$A6,Raw_Sales_Data!$D$2:$D$2528,C$5,Raw_Sales_Data!$C$2:$C$2528,2025) -> 1025893.5 | D6: =SUMIFS(Raw_Sales_Data!$O$2:$O$2528,Raw_Sales_Data!$E$2:$E$2528,$A6,Raw_Sales_Data!$D$2:$D$2528,D$5,Raw_Sales_Data!$C$2:$C$2528,2025) -> 1551611.9 | E6: =SUMIFS(Raw_Sales_Data!$O$2:$O$2528,Raw_Sales_Data!$E$2:$E$2528,$A6,Raw_Sales_Data!$D$2:$D$2528,E$5,Raw_Sales_Data!$C$2:$C$2528,2025) -> 1137705 | F6: =SUMIFS(Raw_Sales_Data!$O$2:$O$2528,Raw_Sales_Data!$E$2:$E$2528,$A6,Raw_Sales_Data!$D$2:$D$2528,F$5,Raw_Sales_Data!$C$2:$C$2528,2025) -> 1727952.9 | G6: =SUMIFS(Raw_Sales_Data!$O$2:$O$2528,Raw_Sales_Data!$E$2:$E$2528,$A6,Raw_Sales_Data!$D$2:$D$2528,G$5,Raw_Sales_Data!$C$2:$C$2528,2025) -> 1816745.7 | H6: =SUMIFS(Raw_Sales_Data!$O$2:$O$2528,Raw_Sales_Data!$E$2:$E$2528,$A6,Raw_Sales_Data!$D$2:$D$2528,H$5,Raw_Sales_Data!$C$2:$C$2528,2025) -> 2492717.7 | I6: =SUMIFS(Raw_Sales_Data!$O$2:$O$2528,Raw_Sales_Data!$E$2:$E$2528,$A6,Raw_Sales_Data!$D$2:$D$2528,I$5,Raw_Sales_Data!$C$2:$C$2528,2025) -> 2263057.4 | ... M6: =SUMIFS(Raw_Sales_Data!$O$2:$O$2528,Raw_Sales_Data!$E$2:$E$2528,$A6,Raw_Sales_Data!$D$2:$D$2528,M$5,Raw_Sales_Data!$C$2:$C$2528,2025) -> 914290.97 | O6: =SUM(B6:M6) -> 17329141
A7: South | B7: =SUMIFS(Raw_Sales_Data!$O$2:$O$2528,Raw_Sales_Data!$E$2:$E$2528,$A7,Raw_Sales_Data!$D$2:$D$2528,B$5,Raw_Sales_Data!$C$2:$C$2528,2025) -> 1218354.6 | C7: =SUMIFS(Raw_Sales_Data!$O$2:$O$2528,Raw_Sales_Data!$E$2:$E$2528,$A7,Raw_Sales_Data!$D$2:$D$2528,C$5,Raw_Sales_Data!$C$2:$C$2528,2025) -> 1656728.8 | D7: =SUMIFS(Raw_Sales_Data!$O$2:$O$2528,Raw_Sales_Data!$E$2:$E$2528,$A7,Raw_Sales_Data!$D$2:$D$2528,D$5,Raw_Sales_Data!$C$2:$C$2528,2025) -> 984737.24 | E7: =SUMIFS(Raw_Sales_Data!$O$2:$O$2528,Raw_Sales_Data!$E$2:$E$2528,$A7,Raw_Sales_Data!$D$2:$D$2528,E$5,Raw_Sales_Data!$C$2:$C$2528,2025) -> 928050.03 | F7: =SUMIFS(Raw_Sales_Data!$O$2:$O$2528,Raw_Sales_Data!$E$2:$E$2528,$A7,Raw_Sales_Data!$D$2:$D$2528,F$5,Raw_Sales_Data!$C$2:$C$2528,2025) -> 2324683.4 | G7: =SUMIFS(Raw_Sales_Data!$O$2:$O$2528,Raw_Sales_Data!$E$2:$E$2528,$A7,Raw_Sales_Data!$D$2:$D$2528,G$5,Raw_Sales_Data!$C$2:$C$2528,2025) -> 808543.41 | H7: =SUMIFS(Raw_Sales_Data!$O$2:$O$2528,Raw_Sales_Data!$E$2:$E$2528,$A7,Raw_Sales_Data!$D$2:$D$2528,H$5,Raw_Sales_Data!$C$2:$C$2528,2025) -> 1313561.3 | I7: =SUMIFS(Raw_Sales_Data!$O$2:$O$2528,Raw_Sales_Data!$E$2:$E$2528,$A7,Raw_Sales_Data!$D$2:$D$2528,I$5,Raw_Sales_Data!$C$2:$C$2528,2025) -> 887562.38 | ... M7: =SUMIFS(Raw_Sales_Data!$O$2:$O$2528,Raw_Sales_Data!$E$2:$E$2528,$A7,Raw_Sales_Data!$D$2:$D$2528,M$5,Raw_Sales_Data!$C$2:$C$2528,2025) -> 1800397.8 | O7: =SUM(B7:M7) -> 16855737
A8: West | B8: =SUMIFS(Raw_Sales_Data!$O$2:$O$2528,Raw_Sales_Data!$E$2:$E$2528,$A8,Raw_Sales_Data!$D$2:$D$2528,B$5,Raw_Sales_Data!$C$2:$C$2528,2025) -> 2090411.9 | C8: =SUMIFS(Raw_Sales_Data!$O$2:$O$2528,Raw_Sales_Data!$E$2:$E$2528,$A8,Raw_Sales_Data!$D$2:$D$2528,C$5,Raw_Sales_Data!$C$2:$C$2528,2025) -> 960402.27 | D8: =SUMIFS(Raw_Sales_Data!$O$2:$O$2528,Raw_Sales_Data!$E$2:$E$2528,$A8,Raw_Sales_Data!$D$2:$D$2528,D$5,Raw_Sales_Data!$C$2:$C$2528,2025) -> 1730817.5 | E8: =SUMIFS(Raw_Sales_Data!$O$2:$O$2528,Raw_Sales_Data!$E$2:$E$2528,$A8,Raw_Sales_Data!$D$2:$D$2528,E$5,Raw_Sales_Data!$C$2:$C$2528,2025) -> 1539830.7 | F8: =SUMIFS(Raw_Sales_Data!$O$2:$O$2528,Raw_Sales_Data!$E$2:$E$2528,$A8,Raw_Sales_Data!$D$2:$D$2528,F$5,Raw_Sales_Data!$C$2:$C$2528,2025) -> 1609639 | G8: =SUMIFS(Raw_Sales_Data!$O$2:$O$2528,Raw_Sales_Data!$E$2:$E$2528,$A8,Raw_Sales_Data!$D$2:$D$2528,G$5,Raw_Sales_Data!$C$2:$C$2528,2025) -> 1296485.7 | H8: =SUMIFS(Raw_Sales_Data!$O$2:$O$2528,Raw_Sales_Data!$E$2:$E$2528,$A8,Raw_Sales_Data!$D$2:$D$2528,H$5,Raw_Sales_Data!$C$2:$C$2528,2025) -> 1463665.4 | I8: =SUMIFS(Raw_Sales_Data!$O$2:$O$2528,Raw_Sales_Data!$E$2:$E$2528,$A8,Raw_Sales_Data!$D$2:$D$2528,I$5,Raw_Sales_Data!$C$2:$C$2528,2025) -> 982236.32 | ... M8: =SUMIFS(Raw_Sales_Data!$O$2:$O$2528,Raw_Sales_Data!$E$2:$E$2528,$A8,Raw_Sales_Data!$D$2:$D$2528,M$5,Raw_Sales_Data!$C$2:$C$2528,2025) -> 1564714.7 | O8: =SUM(B8:M8) -> 16874277
A9: East | B9: =SUMIFS(Raw_Sales_Data!$O$2:$O$2528,Raw_Sales_Data!$E$2:$E$2528,$A9,Raw_Sales_Data!$D$2:$D$2528,B$5,Raw_Sales_Data!$C$2:$C$2528,2025) -> 2971524.1 | C9: =SUMIFS(Raw_Sales_Data!$O$2:$O$2528,Raw_Sales_Data!$E$2:$E$2528,$A9,Raw_Sales_Data!$D$2:$D$2528,C$5,Raw_Sales_Data!$C$2:$C$2528,2025) -> 1168552.9 | D9: =SUMIFS(Raw_Sales_Data!$O$2:$O$2528,Raw_Sales_Data!$E$2:$E$2528,$A9,Raw_Sales_Data!$D$2:$D$2528,D$5,Raw_Sales_Data!$C$2:$C$2528,2025) -> 931985.45 | E9: =SUMIFS(Raw_Sales_Data!$O$2:$O$2528,Raw_Sales_Data!$E$2:$E$2528,$A9,Raw_Sales_Data!$D$2:$D$2528,E$5,Raw_Sales_Data!$C$2:$C$2528,2025) -> 1001899.1 | F9: =SUMIFS(Raw_Sales_Data!$O$2:$O$2528,Raw_Sales_Data!$E$2:$E$2528,$A9,Raw_Sales_Data!$D$2:$D$2528,F$5,Raw_Sales_Data!$C$2:$C$2528,2025) -> 1858650.3 | G9: =SUMIFS(Raw_Sales_Data!$O$2:$O$2528,Raw_Sales_Data!$E$2:$E$2528,$A9,Raw_Sales_Data!$D$2:$D$2528,G$5,Raw_Sales_Data!$C$2:$C$2528,2025) -> 3699088.8 | H9: =SUMIFS(Raw_Sales_Data!$O$2:$O$2528,Raw_Sales_Data!$E$2:$E$2528,$A9,Raw_Sales_Data!$D$2:$D$2528,H$5,Raw_Sales_Data!$C$2:$C$2528,2025) -> 1955626.8 | I9: =SUMIFS(Raw_Sales_Data!$O$2:$O$2528,Raw_Sales_Data!$E$2:$E$2528,$A9,Raw_Sales_Data!$D$2:$D$2528,I$5,Raw_Sales_Data!$C$2:$C$2528,2025) -> 1115398.7 | ... M9: =SUMIFS(Raw_Sales_Data!$O$2:$O$2528,Raw_Sales_Data!$E$2:$E$2528,$A9,Raw_Sales_Data!$D$2:$D$2528,M$5,Raw_Sales_Data!$C$2:$C$2528,2025) -> 890111.41 | O9: =SUM(B9:M9) -> 18993257
A10: Total | B10: =SUM(B6:B9) -> 6995127.8 | C10: =SUM(C6:C9) -> 4811577.5 | D10: =SUM(D6:D9) -> 5199152 | E10: =SUM(E6:E9) -> 4607484.8 | F10: =SUM(F6:F9) -> 7520925.6 | G10: =SUM(G6:G9) -> 7620863.7 | H10: =SUM(H6:H9) -> 7225571.2 | I10: =SUM(I6:I9) -> 5248254.8 | ... M10: =SUM(M6:M9) -> 5169514.9
A13: Category Performance Summary
A14: Category | B14: Total Revenue | C14: Total Profit | D14: Avg Margin % | E14: Units Sold
A15: Electronics | B15: =SUMIFS(Raw_Sales_Data!$O$2:$O$2528,Raw_Sales_Data!$G$2:$G$2528,A15) -> 68609051 | C15: =SUMIFS(Raw_Sales_Data!$Q$2:$Q$2528,Raw_Sales_Data!$G$2:$G$2528,A15) -> 23826161 | D15: =IF(B15=0,0,C15/B15) -> 0.34727432 | E15: =SUMIFS(Raw_Sales_Data!$K$2:$K$2528,Raw_Sales_Data!$G$2:$G$2528,A15) -> 3610
A16: Furniture | B16: =SUMIFS(Raw_Sales_Data!$O$2:$O$2528,Raw_Sales_Data!$G$2:$G$2528,A16) -> 26154327 | C16: =SUMIFS(Raw_Sales_Data!$Q$2:$Q$2528,Raw_Sales_Data!$G$2:$G$2528,A16) -> 9235003 | D16: =IF(B16=0,0,C16/B16) -> 0.35309657 | E16: =SUMIFS(Raw_Sales_Data!$K$2:$K$2528,Raw_Sales_Data!$G$2:$G$2528,A16) -> 4074
A17: Apparel | B17: =SUMIFS(Raw_Sales_Data!$O$2:$O$2528,Raw_Sales_Data!$G$2:$G$2528,A17) -> 8103017.4 | C17: =SUMIFS(Raw_Sales_Data!$Q$2:$Q$2528,Raw_Sales_Data!$G$2:$G$2528,A17) -> 2877311.3 | D17: =IF(B17=0,0,C17/B17) -> 0.35509134 | E17: =SUMIFS(Raw_Sales_Data!$K$2:$K$2528,Raw_Sales_Data!$G$2:$G$2528,A17) -> 4327
A18: Home Appliances | B18: =SUMIFS(Raw_Sales_Data!$O$2:$O$2528,Raw_Sales_Data!$G$2:$G$2528,A18) -> 33017206 | C18: =SUMIFS(Raw_Sales_Data!$Q$2:$Q$2528,Raw_Sales_Data!$G$2:$G$2528,A18) -> 11613131 | D18: =IF(B18=0,0,C18/B18) -> 0.35172968 | E18: =SUMIFS(Raw_Sales_Data!$K$2:$K$2528,Raw_Sales_Data!$G$2:$G$2528,A18) -> 4294
A21: Salesperson Performance (Ranked by Profit)
A22: Salesperson | B22: Total Revenue | C22: Total Profit | D22: Rank
A23: Aarav Shah | B23: =SUMIFS(Raw_Sales_Data!$O$2:$O$2528,Raw_Sales_Data!$I$2:$I$2528,A23) -> 13592167 | C23: =SUMIFS(Raw_Sales_Data!$Q$2:$Q$2528,Raw_Sales_Data!$I$2:$I$2528,A23) -> 4850921.1 | D23: =RANK(C23,C23:C32) -> 3
A24: Priya Nair | B24: =SUMIFS(Raw_Sales_Data!$O$2:$O$2528,Raw_Sales_Data!$I$2:$I$2528,A24) -> 13698539 | C24: =SUMIFS(Raw_Sales_Data!$Q$2:$Q$2528,Raw_Sales_Data!$I$2:$I$2528,A24) -> 4833031.5 | D24: =RANK(C24,C23:C32) -> 4
A25: Rohan Mehta | B25: =SUMIFS(Raw_Sales_Data!$O$2:$O$2528,Raw_Sales_Data!$I$2:$I$2528,A25) -> 15882289 | C25: =SUMIFS(Raw_Sales_Data!$Q$2:$Q$2528,Raw_Sales_Data!$I$2:$I$2528,A25) -> 5591192.8 | D25: =RANK(C25,C23:C32) -> 1
A26: Sneha Kulkarni | B26: =SUMIFS(Raw_Sales_Data!$O$2:$O$2528,Raw_Sales_Data!$I$2:$I$2528,A26) -> 13460978 | C26: =SUMIFS(Raw_Sales_Data!$Q$2:$Q$2528,Raw_Sales_Data!$I$2:$I$2528,A26) -> 4787603.4 | D26: =RANK(C26,C23:C32) -> 5
A27: Vikram Rao | B27: =SUMIFS(Raw_Sales_Data!$O$2:$O$2528,Raw_Sales_Data!$I$2:$I$2528,A27) -> 12012333 | C27: =SUMIFS(Raw_Sales_Data!$Q$2:$Q$2528,Raw_Sales_Data!$I$2:$I$2528,A27) -> 4094033.8 | D27: =RANK(C27,C23:C32) -> 10
A28: Ananya Iyer | B28: =SUMIFS(Raw_Sales_Data!$O$2:$O$2528,Raw_Sales_Data!$I$2:$I$2528,A28) -> 12408040 | C28: =SUMIFS(Raw_Sales_Data!$Q$2:$Q$2528,Raw_Sales_Data!$I$2:$I$2528,A28) -> 4314727.7 | D28: =RANK(C28,C23:C32) -> 9
A29: Karan Malhotra | B29: =SUMIFS(Raw_Sales_Data!$O$2:$O$2528,Raw_Sales_Data!$I$2:$I$2528,A29) -> 12778212 | C29: =SUMIFS(Raw_Sales_Data!$Q$2:$Q$2528,Raw_Sales_Data!$I$2:$I$2528,A29) -> 4703168.8 | D29: =RANK(C29,C23:C32) -> 6
A30: Divya Reddy | B30: =SUMIFS(Raw_Sales_Data!$O$2:$O$2528,Raw_Sales_Data!$I$2:$I$2528,A30) -> 13284893 | C30: =SUMIFS(Raw_Sales_Data!$Q$2:$Q$2528,Raw_Sales_Data!$I$2:$I$2528,A30) -> 4521625.8 | D30: =RANK(C30,C23:C32) -> 8
A31: Arjun Kapoor | B31: =SUMIFS(Raw_Sales_Data!$O$2:$O$2528,Raw_Sales_Data!$I$2:$I$2528,A31) -> 15277537 | C31: =SUMIFS(Raw_Sales_Data!$Q$2:$Q$2528,Raw_Sales_Data!$I$2:$I$2528,A31) -> 5185426.2 | D31: =RANK(C31,C23:C32) -> 2
A32: Neha Joshi | B32: =SUMIFS(Raw_Sales_Data!$O$2:$O$2528,Raw_Sales_Data!$I$2:$I$2528,A32) -> 13488612 | C32: =SUMIFS(Raw_Sales_Data!$Q$2:$Q$2528,Raw_Sales_Data!$I$2:$I$2528,A32) -> 4669876.1 | D32: =RANK(C32,C23:C32) -> 7

Sheet What_If_Analysis
A1: What-If & Scenario Analysis
A2: Change the blue Scenario dropdown, or try Data > What-If Analysis > Goal Seek on Net Profit
A4: Scenario Manager Inputs
A5: Scenario | B5: Likely
B6: Best | C6: Likely | D6: Worst
A7: Avg Discount % | B7: 0.03 | C7: 0.08 | D7: 0.15
A8: Revenue Growth % | B8: 0.18 | C8: 0.08 | D8: -0.05
A9: Cost Ratio | B9: 0.6 | C9: 0.65 | D9: 0.72
A11: Selected Scenario Output
A12: Active Avg Discount %: | B12: =INDEX(B7:D7,MATCH(B5,B6:D6,0)) -> 0.08
A13: Active Revenue Growth %: | B13: =INDEX(B8:D8,MATCH(B5,B6:D6,0)) -> 0.08
A14: Active Cost Ratio: | B14: =INDEX(B9:D9,MATCH(B5,B6:D6,0)) -> 0.65
A15: Current Total Revenue (₹): | B15: =SUM(Raw_Sales_Data!$O$2:$O$2528) -> 1.358836e+08
A16: Projected Revenue Next Year (₹): | B16: =B15*(1+B13)*(1-B12) -> 1.3501395e+08
A17: Projected Cost (₹): | B17: =B16*B14 -> 87759065
A18: Projected Net Profit (₹): | B18: =B16-B17 -> 47254881
A20: Sensitivity: Discount % vs Projected Net Profit
A21: Discount % | B21: Net Profit (₹)
A22: 0 | B22: =(B15*(1+B13)*(1-A22))-(B15*(1+B13)*(1-A22)*B14) -> 51364001
A23: 0.05 | B23: =(B15*(1+B13)*(1-A23))-(B15*(1+B13)*(1-A23)*B14) -> 48795801
A24: 0.1 | B24: =(B15*(1+B13)*(1-A24))-(B15*(1+B13)*(1-A24)*B14) -> 46227601
A25: 0.15 | B25: =(B15*(1+B13)*(1-A25))-(B15*(1+B13)*(1-A25)*B14) -> 43659401
A26: 0.2 | B26: =(B15*(1+B13)*(1-A26))-(B15*(1+B13)*(1-A26)*B14) -> 41091201
A27: 0.25 | B27: =(B15*(1+B13)*(1-A27))-(B15*(1+B13)*(1-A27)*B14) -> 38523001
A28: 0.3 | B28: =(B15*(1+B13)*(1-A28))-(B15*(1+B13)*(1-A28)*B14) -> 35954801
